LICENSE
README.md
setup.py
utils/__init__.py
utils/bioinformatics.py
utils/file.py
utils/time.py
utils_wyj.egg-info/PKG-INFO
utils_wyj.egg-info/SOURCES.txt
utils_wyj.egg-info/dependency_links.txt
utils_wyj.egg-info/top_level.txt