Metadata-Version: 2.1
Name: utils-wyj
Version: 0.0.3
Summary: Yujue Wang's tool library
Home-page: https://github.com/spsc83/utils
Author: Yujue Wang
Author-email: spsc83@gmail.com
License: MIT License
Keywords: tools
Platform: any
License-File: LICENSE
